[
  {
    "time": "2024-09-28",
    "close": 601.5
  },
  {
    "time": "2024-09-29",
    "close": 595.9
  },
  {
    "time": "2024-09-30",
    "close": 567.6
  },
  {
    "time": "2024-10-01",
    "close": 547.5
  },
  {
    "time": "2024-10-02",
    "close": 542.7
  },
  {
    "time": "2024-10-03",
    "close": 545.0
  },
  {
    "time": "2024-10-04",
    "close": 555.7
  },
  {
    "time": "2024-10-05",
    "close": 563.1
  },
  {
    "time": "2024-10-06",
    "close": 570.4
  },
  {
    "time": "2024-10-07",
    "close": 564.3
  },
  {
    "time": "2024-10-08",
    "close": 580.7
  },
  {
    "time": "2024-10-09",
    "close": 570.1
  },
  {
    "time": "2024-10-10",
    "close": 563.4
  },
  {
    "time": "2024-10-11",
    "close": 573.5
  },
  {
    "time": "2024-10-12",
    "close": 576.7
  },
  {
    "time": "2024-10-13",
    "close": 572.2
  },
  {
    "time": "2024-10-14",
    "close": 589.3
  },
  {
    "time": "2024-10-15",
    "close": 594.6
  },
  {
    "time": "2024-10-16",
    "close": 600.9
  },
  {
    "time": "2024-10-17",
    "close": 592.7
  },
  {
    "time": "2024-10-18",
    "close": 599.0
  },
  {
    "time": "2024-10-19",
    "close": 597.8
  },
  {
    "time": "2024-10-20",
    "close": 605.8
  },
  {
    "time": "2024-10-21",
    "close": 598.6
  },
  {
    "time": "2024-10-22",
    "close": 593.4
  },
  {
    "time": "2024-10-23",
    "close": 584.5
  },
  {
    "time": "2024-10-24",
    "close": 594.1
  },
  {
    "time": "2024-10-25",
    "close": 574.6
  },
  {
    "time": "2024-10-26",
    "close": 582.8
  },
  {
    "time": "2024-10-27",
    "close": 588.8
  },
  {
    "time": "2024-10-28",
    "close": 600.8
  },
  {
    "time": "2024-10-29",
    "close": 606.1
  },
  {
    "time": "2024-10-30",
    "close": 595.6
  },
  {
    "time": "2024-10-31",
    "close": 576.0
  },
  {
    "time": "2024-11-01",
    "close": 573.0
  },
  {
    "time": "2024-11-02",
    "close": 568.3
  },
  {
    "time": "2024-11-03",
    "close": 557.8
  },
  {
    "time": "2024-11-04",
    "close": 552.2
  },
  {
    "time": "2024-11-05",
    "close": 563.5
  },
  {
    "time": "2024-11-06",
    "close": 592.5
  },
  {
    "time": "2024-11-07",
    "close": 598.6
  },
  {
    "time": "2024-11-08",
    "close": 597.9
  },
  {
    "time": "2024-11-09",
    "close": 624.9
  },
  {
    "time": "2024-11-10",
    "close": 627.6
  },
  {
    "time": "2024-11-11",
    "close": 660.1
  },
  {
    "time": "2024-11-12",
    "close": 625.8
  },
  {
    "time": "2024-11-13",
    "close": 621.5
  },
  {
    "time": "2024-11-14",
    "close": 622.6
  },
  {
    "time": "2024-11-15",
    "close": 619.3
  },
  {
    "time": "2024-11-16",
    "close": 622.8
  },
  {
    "time": "2024-11-17",
    "close": 618.7
  },
  {
    "time": "2024-11-18",
    "close": 619.2
  },
  {
    "time": "2024-11-19",
    "close": 616.3
  },
  {
    "time": "2024-11-20",
    "close": 605.8
  },
  {
    "time": "2024-11-21",
    "close": 622.5
  },
  {
    "time": "2024-11-22",
    "close": 633.3
  },
  {
    "time": "2024-11-23",
    "close": 650.6
  },
  {
    "time": "2024-11-24",
    "close": 660.1
  },
  {
    "time": "2024-11-25",
    "close": 636.2
  },
  {
    "time": "2024-11-26",
    "close": 613.5
  },
  {
    "time": "2024-11-27",
    "close": 644.8
  },
  {
    "time": "2024-11-28",
    "close": 654.1
  },
  {
    "time": "2024-11-29",
    "close": 655.0
  },
  {
    "time": "2024-11-30",
    "close": 653.9
  },
  {
    "time": "2024-12-01",
    "close": 656.5
  },
  {
    "time": "2024-12-02",
    "close": 648.0
  },
  {
    "time": "2024-12-03",
    "close": 735.5
  },
  {
    "time": "2024-12-04",
    "close": 740.4
  },
  {
    "time": "2024-12-05",
    "close": 717.6
  },
  {
    "time": "2024-12-06",
    "close": 731.1
  },
  {
    "time": "2024-12-07",
    "close": 750.2
  },
  {
    "time": "2024-12-08",
    "close": 742.6
  },
  {
    "time": "2024-12-09",
    "close": 690.1
  },
  {
    "time": "2024-12-10",
    "close": 677.3
  },
  {
    "time": "2024-12-11",
    "close": 711.5
  },
  {
    "time": "2024-12-12",
    "close": 706.1
  },
  {
    "time": "2024-12-13",
    "close": 725.8
  },
  {
    "time": "2024-12-14",
    "close": 715.6
  },
  {
    "time": "2024-12-15",
    "close": 718.3
  },
  {
    "time": "2024-12-16",
    "close": 720.4
  },
  {
    "time": "2024-12-17",
    "close": 717.5
  },
  {
    "time": "2024-12-18",
    "close": 686.1
  },
  {
    "time": "2024-12-19",
    "close": 665.2
  },
  {
    "time": "2024-12-20",
    "close": 678.5
  },
  {
    "time": "2024-12-21",
    "close": 663.2
  },
  {
    "time": "2024-12-22",
    "close": 649.5
  },
  {
    "time": "2024-12-23",
    "close": 693.4
  },
  {
    "time": "2024-12-24",
    "close": 696.7
  },
  {
    "time": "2024-12-25",
    "close": 702.5
  },
  {
    "time": "2024-12-26",
    "close": 688.9
  },
  {
    "time": "2024-12-27",
    "close": 691.2
  },
  {
    "time": "2024-12-28",
    "close": 721.7
  },
  {
    "time": "2024-12-29",
    "close": 694.2
  },
  {
    "time": "2024-12-30",
    "close": 704.6
  },
  {
    "time": "2024-12-31",
    "close": 701.5
  },
  {
    "time": "2025-01-01",
    "close": 707.1
  },
  {
    "time": "2025-01-02",
    "close": 705.7
  },
  {
    "time": "2025-01-03",
    "close": 714.6
  },
  {
    "time": "2025-01-04",
    "close": 713.4
  },
  {
    "time": "2025-01-05",
    "close": 709.2
  },
  {
    "time": "2025-01-06",
    "close": 729.8
  },
  {
    "time": "2025-01-07",
    "close": 698.1
  },
  {
    "time": "2025-01-08",
    "close": 696.2
  },
  {
    "time": "2025-01-09",
    "close": 685.6
  },
  {
    "time": "2025-01-10",
    "close": 693.0
  },
  {
    "time": "2025-01-11",
    "close": 696.8
  },
  {
    "time": "2025-01-12",
    "close": 693.1
  },
  {
    "time": "2025-01-13",
    "close": 688.6
  },
  {
    "time": "2025-01-14",
    "close": 699.1
  },
  {
    "time": "2025-01-15",
    "close": 714.7
  },
  {
    "time": "2025-01-16",
    "close": 708.2
  },
  {
    "time": "2025-01-17",
    "close": 721.8
  },
  {
    "time": "2025-01-18",
    "close": 708.8
  },
  {
    "time": "2025-01-19",
    "close": 682.5
  },
  {
    "time": "2025-01-20",
    "close": 681.7
  },
  {
    "time": "2025-01-21",
    "close": 692.2
  },
  {
    "time": "2025-01-22",
    "close": 695.1
  },
  {
    "time": "2025-01-23",
    "close": 690.0
  },
  {
    "time": "2025-01-24",
    "close": 680.3
  },
  {
    "time": "2025-01-25",
    "close": 686.2
  },
  {
    "time": "2025-01-26",
    "close": 667.2
  },
  {
    "time": "2025-01-27",
    "close": 680.1
  },
  {
    "time": "2025-01-28",
    "close": 661.2
  },
  {
    "time": "2025-01-29",
    "close": 667.9
  },
  {
    "time": "2025-01-30",
    "close": 677.6
  },
  {
    "time": "2025-01-31",
    "close": 677.4
  },
  {
    "time": "2025-02-01",
    "close": 653.1
  },
  {
    "time": "2025-02-02",
    "close": 617.4
  },
  {
    "time": "2025-02-03",
    "close": 617.6
  },
  {
    "time": "2025-02-04",
    "close": 572.9
  },
  {
    "time": "2025-02-05",
    "close": 569.5
  },
  {
    "time": "2025-02-06",
    "close": 572.2
  },
  {
    "time": "2025-02-07",
    "close": 578.0
  },
  {
    "time": "2025-02-08",
    "close": 612.8
  },
  {
    "time": "2025-02-09",
    "close": 616.2
  },
  {
    "time": "2025-02-10",
    "close": 618.8
  },
  {
    "time": "2025-02-11",
    "close": 642.3
  },
  {
    "time": "2025-02-12",
    "close": 697.2
  },
  {
    "time": "2025-02-13",
    "close": 665.2
  },
  {
    "time": "2025-02-14",
    "close": 659.8
  },
  {
    "time": "2025-02-15",
    "close": 662.3
  },
  {
    "time": "2025-02-16",
    "close": 673.4
  },
  {
    "time": "2025-02-17",
    "close": 667.8
  },
  {
    "time": "2025-02-18",
    "close": 648.1
  },
  {
    "time": "2025-02-19",
    "close": 653.9
  },
  {
    "time": "2025-02-20",
    "close": 656.8
  },
  {
    "time": "2025-02-21",
    "close": 647.4
  },
  {
    "time": "2025-02-22",
    "close": 668.9
  },
  {
    "time": "2025-02-23",
    "close": 658.4
  },
  {
    "time": "2025-02-24",
    "close": 614.8
  },
  {
    "time": "2025-02-25",
    "close": 623.2
  },
  {
    "time": "2025-02-26",
    "close": 611.2
  },
  {
    "time": "2025-02-27",
    "close": 605.5
  },
  {
    "time": "2025-02-28",
    "close": 588.3
  },
  {
    "time": "2025-03-01",
    "close": 608.3
  },
  {
    "time": "2025-03-02",
    "close": 624.3
  },
  {
    "time": "2025-03-03",
    "close": 576.1
  },
  {
    "time": "2025-03-04",
    "close": 584.1
  },
  {
    "time": "2025-03-05",
    "close": 598.6
  },
  {
    "time": "2025-03-06",
    "close": 596.7
  },
  {
    "time": "2025-03-07",
    "close": 594.9
  },
  {
    "time": "2025-03-08",
    "close": 593.4
  },
  {
    "time": "2025-03-09",
    "close": 554.8
  },
  {
    "time": "2025-03-10",
    "close": 531.5
  },
  {
    "time": "2025-03-11",
    "close": 551.9
  },
  {
    "time": "2025-03-12",
    "close": 570.0
  },
  {
    "time": "2025-03-13",
    "close": 580.0
  },
  {
    "time": "2025-03-14",
    "close": 588.2
  },
  {
    "time": "2025-03-15",
    "close": 620.1
  },
  {
    "time": "2025-03-16",
    "close": 602.5
  },
  {
    "time": "2025-03-17",
    "close": 632.3
  },
  {
    "time": "2025-03-18",
    "close": 628.3
  },
  {
    "time": "2025-03-19",
    "close": 619.2
  },
  {
    "time": "2025-03-20",
    "close": 630.4
  },
  {
    "time": "2025-03-21",
    "close": 635.1
  },
  {
    "time": "2025-03-22",
    "close": 626.9
  },
  {
    "time": "2025-03-23",
    "close": 624.4
  },
  {
    "time": "2025-03-24",
    "close": 637.4
  },
  {
    "time": "2025-03-25",
    "close": 630.4
  },
  {
    "time": "2025-03-26",
    "close": 618.3
  },
  {
    "time": "2025-03-27",
    "close": 637.6
  },
  {
    "time": "2025-03-28",
    "close": 619.8
  },
  {
    "time": "2025-03-29",
    "close": 603.1
  },
  {
    "time": "2025-03-30",
    "close": 602.3
  },
  {
    "time": "2025-03-31",
    "close": 605.0
  },
  {
    "time": "2025-04-01",
    "close": 611.2
  },
  {
    "time": "2025-04-02",
    "close": 590.4
  },
  {
    "time": "2025-04-03",
    "close": 592.4
  },
  {
    "time": "2025-04-04",
    "close": 597.4
  },
  {
    "time": "2025-04-05",
    "close": 593.2
  },
  {
    "time": "2025-04-06",
    "close": 555.2
  },
  {
    "time": "2025-04-07",
    "close": 554.6
  },
  {
    "time": "2025-04-08",
    "close": 553.3
  },
  {
    "time": "2025-04-09",
    "close": 582.2
  },
  {
    "time": "2025-04-10",
    "close": 577.6
  },
  {
    "time": "2025-04-11",
    "close": 585.8
  },
  {
    "time": "2025-04-12",
    "close": 597.2
  },
  {
    "time": "2025-04-13",
    "close": 584.0
  },
  {
    "time": "2025-04-14",
    "close": 584.3
  },
  {
    "time": "2025-04-15",
    "close": 579.6
  },
  {
    "time": "2025-04-16",
    "close": 582.7
  },
  {
    "time": "2025-04-17",
    "close": 590.3
  },
  {
    "time": "2025-04-18",
    "close": 591.6
  },
  {
    "time": "2025-04-19",
    "close": 591.5
  },
  {
    "time": "2025-04-20",
    "close": 592.5
  },
  {
    "time": "2025-04-21",
    "close": 597.3
  },
  {
    "time": "2025-04-22",
    "close": 618.6
  },
  {
    "time": "2025-04-23",
    "close": 605.7
  },
  {
    "time": "2025-04-24",
    "close": 601.7
  },
  {
    "time": "2025-04-25",
    "close": 600.4
  },
  {
    "time": "2025-04-26",
    "close": 607.4
  },
  {
    "time": "2025-04-27",
    "close": 603.8
  },
  {
    "time": "2025-04-28",
    "close": 606.4
  },
  {
    "time": "2025-04-29",
    "close": 601.2
  },
  {
    "time": "2025-04-30",
    "close": 600.1
  },
  {
    "time": "2025-05-01",
    "close": 599.9
  },
  {
    "time": "2025-05-02",
    "close": 601.1
  },
  {
    "time": "2025-05-03",
    "close": 599.7
  },
  {
    "time": "2025-05-04",
    "close": 586.6
  },
  {
    "time": "2025-05-05",
    "close": 598.0
  },
  {
    "time": "2025-05-06",
    "close": 602.7
  },
  {
    "time": "2025-05-07",
    "close": 603.0
  },
  {
    "time": "2025-05-08",
    "close": 629.2
  },
  {
    "time": "2025-05-09",
    "close": 666.3
  },
  {
    "time": "2025-05-10",
    "close": 663.9
  },
  {
    "time": "2025-05-11",
    "close": 650.7
  },
  {
    "time": "2025-05-12",
    "close": 660.3
  },
  {
    "time": "2025-05-13",
    "close": 664.4
  },
  {
    "time": "2025-05-14",
    "close": 652.7
  },
  {
    "time": "2025-05-15",
    "close": 651.7
  },
  {
    "time": "2025-05-16",
    "close": 646.4
  },
  {
    "time": "2025-05-17",
    "close": 640.0
  },
  {
    "time": "2025-05-18",
    "close": 651.7
  },
  {
    "time": "2025-05-19",
    "close": 649.8
  },
  {
    "time": "2025-05-20",
    "close": 650.1
  },
  {
    "time": "2025-05-21",
    "close": 673.8
  },
  {
    "time": "2025-05-22",
    "close": 686.3
  },
  {
    "time": "2025-05-23",
    "close": 656.9
  },
  {
    "time": "2025-05-24",
    "close": 667.9
  },
  {
    "time": "2025-05-25",
    "close": 669.5
  },
  {
    "time": "2025-05-26",
    "close": 674.3
  },
  {
    "time": "2025-05-27",
    "close": 687.1
  },
  {
    "time": "2025-05-28",
    "close": 687.0
  },
  {
    "time": "2025-05-29",
    "close": 675.2
  },
  {
    "time": "2025-05-30",
    "close": 655.7
  },
  {
    "time": "2025-05-31",
    "close": 658.4
  },
  {
    "time": "2025-06-01",
    "close": 661.2
  },
  {
    "time": "2025-06-02",
    "close": 666.3
  },
  {
    "time": "2025-06-03",
    "close": 661.6
  },
  {
    "time": "2025-06-04",
    "close": 663.3
  },
  {
    "time": "2025-06-05",
    "close": 634.0
  },
  {
    "time": "2025-06-06",
    "close": 643.5
  },
  {
    "time": "2025-06-07",
    "close": 651.4
  },
  {
    "time": "2025-06-08",
    "close": 652.3
  },
  {
    "time": "2025-06-09",
    "close": 665.8
  },
  {
    "time": "2025-06-10",
    "close": 673.6
  },
  {
    "time": "2025-06-11",
    "close": 667.7
  },
  {
    "time": "2025-06-12",
    "close": 655.2
  },
  {
    "time": "2025-06-13",
    "close": 655.6
  },
  {
    "time": "2025-06-14",
    "close": 646.2
  },
  {
    "time": "2025-06-15",
    "close": 648.5
  },
  {
    "time": "2025-06-16",
    "close": 651.0
  },
  {
    "time": "2025-06-17",
    "close": 648.6
  },
  {
    "time": "2025-06-18",
    "close": 645.2
  },
  {
    "time": "2025-06-19",
    "close": 644.8
  },
  {
    "time": "2025-06-20",
    "close": 641.9
  },
  {
    "time": "2025-06-21",
    "close": 629.5
  },
  {
    "time": "2025-06-22",
    "close": 616.4
  },
  {
    "time": "2025-06-23",
    "close": 641.1
  },
  {
    "time": "2025-06-24",
    "close": 643.8
  },
  {
    "time": "2025-06-25",
    "close": 646.3
  },
  {
    "time": "2025-06-26",
    "close": 642.5
  },
  {
    "time": "2025-06-27",
    "close": 646.2
  },
  {
    "time": "2025-06-28",
    "close": 648.9
  },
  {
    "time": "2025-06-29",
    "close": 655.1
  },
  {
    "time": "2025-06-30",
    "close": 657.1
  },
  {
    "time": "2025-07-01",
    "close": 646.7
  },
  {
    "time": "2025-07-02",
    "close": 660.2
  },
  {
    "time": "2025-07-03",
    "close": 663.9
  },
  {
    "time": "2025-07-04",
    "close": 654.1
  },
  {
    "time": "2025-07-05",
    "close": 656.5
  },
  {
    "time": "2025-07-06",
    "close": 663.6
  },
  {
    "time": "2025-07-07",
    "close": 661.3
  },
  {
    "time": "2025-07-08",
    "close": 660.8
  },
  {
    "time": "2025-07-09",
    "close": 669.3
  },
  {
    "time": "2025-07-10",
    "close": 685.8
  },
  {
    "time": "2025-07-11",
    "close": 689.9
  },
  {
    "time": "2025-07-12",
    "close": 685.8
  },
  {
    "time": "2025-07-13",
    "close": 691.8
  },
  {
    "time": "2025-07-14",
    "close": 689.3
  },
  {
    "time": "2025-07-15",
    "close": 690.1
  },
  {
    "time": "2025-07-16",
    "close": 709.0
  },
  {
    "time": "2025-07-17",
    "close": 721.3
  },
  {
    "time": "2025-07-18",
    "close": 730.3
  },
  {
    "time": "2025-07-19",
    "close": 733.5
  },
  {
    "time": "2025-07-20",
    "close": 757.0
  },
  {
    "time": "2025-07-21",
    "close": 766.7
  },
  {
    "time": "2025-07-22",
    "close": 786.9
  },
  {
    "time": "2025-07-23",
    "close": 777.0
  },
  {
    "time": "2025-07-24",
    "close": 773.8
  }
]